pyannote/database/__init__.py
pyannote/database/cli.py
pyannote/database/custom.py
pyannote/database/database.py
pyannote/database/file_finder.py
pyannote/database/loader.py
pyannote/database/py.typed
pyannote/database/registry.py
pyannote/database/util.py
pyannote/database/protocol/__init__.py
pyannote/database/protocol/collection.py
pyannote/database/protocol/protocol.py
pyannote/database/protocol/segmentation.py
pyannote/database/protocol/speaker_diarization.py
pyannote/database/protocol/speaker_identification.py
pyannote/database/protocol/speaker_recognition.py
pyannote/database/protocol/speaker_spotting.py
pyannote/database/protocol/speaker_verification.py
pyannote_database-6.1.0.dist-info/METADATA
pyannote_database-6.1.0.dist-info/WHEEL
pyannote_database-6.1.0.dist-info/entry_points.txt
pyannote_database-6.1.0.dist-info/licenses/LICENSE
pyannote_database-6.1.0.dist-info/RECORD
