Metadata-Version: 2.4
Name: pyannote-database
Version: 6.1.0
Summary: Interface to multimedia databases and experimental protocols
Author-email: Hervé BREDIN <herve@pyannote.ai>
License-File: LICENSE
Requires-Python: >=3.10
Requires-Dist: pandas>=2.2.3
Requires-Dist: pyannote-core>=6.0.0
Requires-Dist: pyyaml>=6.0.2
Provides-Extra: cli
Requires-Dist: typer>=0.15.1; extra == 'cli'
Provides-Extra: doc
Requires-Dist: sphinx-rtd-theme>=3.0.2; extra == 'doc'
Requires-Dist: sphinx>=8.1.3; extra == 'doc'
Provides-Extra: test
Requires-Dist: pytest>=8.3.4; extra == 'test'
Provides-Extra: transcription
Requires-Dist: meeteval>=0.4.3; extra == 'transcription'
